thingtalk/__init__.py
thingtalk/app.py
thingtalk/cli.py
thingtalk/dependencies.py
thingtalk/domains/__init__.py
thingtalk/domains/iot.py
thingtalk/mixins.py
thingtalk/models/__init__.py
thingtalk/models/action.py
thingtalk/models/containers.py
thingtalk/models/errors.py
thingtalk/models/event.py
thingtalk/models/property.py
thingtalk/models/thing.py
thingtalk/models/value.py
thingtalk/routers/__init__.py
thingtalk/routers/actions.py
thingtalk/routers/events.py
thingtalk/routers/mqtt.py
thingtalk/routers/properties.py
thingtalk/routers/rules.py
thingtalk/routers/scenes.py
thingtalk/routers/things.py
thingtalk/routers/websockets.py
thingtalk/rule_engine.py
thingtalk/schema.py
thingtalk/toolkits/__init__.py
thingtalk/toolkits/event_bus.py
thingtalk/toolkits/mqtt.py
thingtalk/toolkits/scheduler.py
thingtalk/utils.py
thingtalk-0.8.2.dist-info/LICENSE.txt
thingtalk-0.8.2.dist-info/WHEEL
thingtalk-0.8.2.dist-info/METADATA
thingtalk-0.8.2.dist-info/RECORD
