Metadata-Version: 2.1
Name: thingtalk
Version: 0.8.2
Summary: Web of Things framework, high performance, easy to learn, fast to code, ready for production
Home-page: https://github.com/hidaris/thingtalk
License: MPL-2.0
Keywords: web-of-things,webthing,iot
Author: hidaris
Author-email: zuocool@gmail.com
Requires-Python: >=3.8,<4.0
Classifier: Development Status :: 4 - Beta
Classifier: Intended Audience :: Developers
Classifier: License :: OSI Approved
Classifier: License :: OSI Approved :: Mozilla Public License 2.0 (MPL 2.0)
Classifier: Programming Language :: Python :: 3
Classifier: Programming Language :: Python :: 3.8
Classifier: Programming Language :: Python :: 3.9
Classifier: Programming Language :: Python :: 3.10
Classifier: Programming Language :: Python :: 3.11
Classifier: Programming Language :: Python :: 3.8
Classifier: Programming Language :: Python :: 3.9
Provides-Extra: docs
Requires-Dist: async-cron (>=1.6.2,<2.0.0)
Requires-Dist: cached-property (>=1.5,<2.0); python_version >= "3.7" and python_version < "3.8"
Requires-Dist: email_validator (>=1.1.1,<2.0.0)
Requires-Dist: fastapi (>=0.87,<0.88)
Requires-Dist: ifaddr (>=0.2.0,<0.3.0)
Requires-Dist: jsonschema (>=4.17.0,<5.0.0)
Requires-Dist: loguru (>=0.6.0,<0.7.0)
Requires-Dist: mkdocs-material (>=8.5.0,<9.0.0); extra == "docs"
Requires-Dist: orjson (>=3.8.1,<4.0.0)
Requires-Dist: pyee (>=9.0.0,<10.0.0)
Requires-Dist: uvicorn[standard] (>=0.20.0,<0.21.0)
Requires-Dist: zeroconf (>=0.39.0,<0.40.0)
Project-URL: Bug Tracker, https://github.com/hidaris/thingtalk/issues
Project-URL: Documentation, https://github.com/hidaris/thingtalk/blob/master/README.md
Project-URL: Repository, https://github.com/hidaris/thingtalk
